[
  {
    "targets": [55, 168, 259, 358, 484],
    "numbers": [
      [1, 2, 4, 5, 10, 25],
      [3, 5, 7, 9, 11, 25],
      [5, 6, 9, 11, 20, 25],
      [3, 4, 5, 6, 11, 20],
      [7, 9, 11, 19, 20, 23]
    ],
    "solutions": [
      "10 + 1 = 11. 11 × 5 = 55.",
      "25 - 11 = 14. 7 + 5 = 12. 14 × 12 = 168.",
      "25 + 20 = 45. 45 × 6 = 270. 270 - 11 = 259.",
      "11 × 4 = 44. 5 + 3 = 8. 44 × 8 = 352. 352 + 6 = 358.",
      "9 × 7 = 63. 63 - 19 = 44. 44 × 11 = 484."
    ]
  },
  {
    "targets": [66, 126, 234, 335, 476],
    "numbers": [
      [1, 3, 4, 5, 10, 25],
      [2, 3, 9, 10, 15, 25],
      [3, 4, 6, 8, 9, 11],
      [5, 6, 8, 11, 15, 20],
      [5, 7, 11, 19, 20, 23]
    ],
    "solutions": [
      "25 × 3 = 75. 75 - 10 = 65. 65 + 1 = 66.",
      "10 - 3 = 7. 9 × 7 = 63. 63 × 2 = 126.",
      "9 × 8 = 72. 72 + 6 = 78. 78 × 3 = 234.",
      "11 + 5 = 16. 20 × 16 = 320. 320 + 15 = 335.",
      "23 × 20 = 460. 11 + 5 = 16. 460 + 16 = 476."
    ]
  },
  {
    "targets": [62, 156, 264, 312, 438],
    "numbers": [
      [1, 2, 3, 4, 5, 10],
      [2, 3, 7, 11, 15, 25],
      [4, 5, 6, 7, 9, 25],
      [3, 6, 7, 8, 15, 20],
      [5, 7, 11, 19, 23, 25]
    ],
    "solutions": [
      "5 × 10 = 50. 3 × 4 = 12. 50 + 12 = 62. ",
      "15 × 11 = 165. 165 - 7 = 158. 158 - 2 = 156.",
      "25 + 5 = 30. 30 × 9 = 270. 270 - 6 = 264.",
      "20 + 6 = 26. 15 - 3 = 12. 26 × 12 = 312.",
      "23 × 19 = 437. 437 - 11 = 426. 426 + 7 = 433. 433 + 5 = 438."
    ]
  },
  {
    "targets": [94, 195, 251, 382, 456],
    "numbers": [
      [1, 2, 4, 5, 10, 25],
      [2, 3, 5, 10, 15, 25],
      [3, 5, 7, 9, 11, 20],
      [4, 5, 6, 9, 11, 20],
      [3, 13, 19, 20, 23, 25]
    ],
    "solutions": [
      "5 + 2 = 7. 7 × 10 = 70. 70 + 25 = 95. 95 - 1 = 94.",
      "10 + 3 = 13. 15 × 13 = 195.",
      "7 + 5 = 12. 20 × 12 = 240. 240 + 11 = 251.",
      "11 × 4 = 44. 44 × 9 = 396. 396 - 20 = 376. 376 + 6 = 382.",
      "23 - 20 = 3. 3 / 3 = 1. 25 - 1 = 24. 24 × 19 = 456."
    ]
  },
  {
    "targets": [59, 133, 218, 388, 462],
    "numbers": [
      [2, 3, 5, 11, 15, 25],
      [4, 5, 8, 11, 15, 20],
      [4, 5, 7, 9, 11, 20],
      [3, 5, 9, 20, 23, 25],
      [3, 5, 9, 19, 20, 25]
    ],
    "solutions": [
      "25 - 3 = 22. 22 × 2 = 44. 44 + 15 = 59.",
      "15 × 11 = 165. 8 × 4 = 32. 165 - 32 = 133.",
      "20 × 11 = 220. 220 - 7 = 213. 213 + 5 = 218.",
      "25 - 9 = 16. 23 × 16 = 368. 368 + 20 = 388.",
      "25 × 19 = 475. 475 - 9 = 466. 20 / 5 = 4. 466 - 4 = 462."
    ]
  },
  {
    "targets": [93, 113, 205, 351, 497],
    "numbers": [
      [5, 7, 9, 10, 15, 25],
      [4, 5, 7, 8, 15, 20],
      [3, 4, 6, 9, 11, 15],
      [3, 5, 9, 11, 23, 25],
      [24, 8, 10, 20, 5, 15]
    ],
    "solutions": [
      "15 × 5 = 75. 75 + 25 = 100. 100 - 7 = 93.",
      "15 × 8 = 120. 120 - 7 = 113.",
      "9 × 6 = 54. 54 × 4 = 216. 216 - 11 = 205.",
      "25 + 9 = 34. 34 × 11 = 374. 374 - 23 = 351.",
      "24 × 20 = 480. 480 + 15 = 495, 10 / 5 = 2. 495 + 2 = 497."
    ]
  },
  {
    "targets": [69, 135, 256, 379, 481],
    "numbers": [
      [3, 5, 7, 9, 11, 25],
      [3, 4, 7, 11, 15, 25],
      [3, 6, 7, 9, 15, 20],
      [5, 7, 8, 9, 11, 15],
      [18, 2, 25, 3, 14, 19]
    ],
    "solutions": [
      "25 × 3 = 75. 75 - 11 = 64. 64 + 5 = 69.",
      "15 × 4 = 60. 25 × 3 = 75. 75 + 60 = 135.",
      "15 - 3 = 12. 20 × 12 = 240. 9 + 7 = 16. 240 + 16 = 256.",
      "8 × 5 = 40. 40 × 7 = 280. 11 × 9 = 99. 280 + 99 = 379.",
      "25 × 19 = 475. 18 / 3 = 6. 475 + 6 = 481."
    ]
  },
  {
    "targets": [98, 183, 224, 318, 426],
    "numbers": [
      [2, 3, 5, 7, 10, 25],
      [3, 6, 7, 8, 15, 20],
      [5, 6, 7, 8, 11, 15],
      [5, 6, 9, 11, 15, 20],
      [5, 7, 9, 19, 23, 25]
    ],
    "solutions": [
      "10 × 7 = 70. 70 + 25 = 95. 95 + 3 = 98.",
      "15 - 6 = 9. 20 × 9 = 180. 180 + 3 = 183.",
      "15 + 11 = 26. 26 + 6 = 32. 32 × 7 = 224.",
      "20 + 11 = 31. 31 + 6 = 37. 37 × 9 = 333. 333 - 15 = 318.",
      "23 × 19 = 437. 437 - 25 = 412. 412 + 9 = 421. 421 + 5 = 426."
    ]
  },
  {
    "targets": [58, 199, 201, 333, 421],
    "numbers": [
      [2, 7, 9, 10, 11, 25],
      [5, 7, 8, 9, 11, 25],
      [4, 7, 9, 11, 15, 20],
      [7, 9, 11, 13, 20, 25],
      [5, 6, 10, 11, 18, 12]
    ],
    "solutions": [
      "25 + 11 = 36. 36 - 7 = 29. 29 × 2 = 58.",
      "25 + 5 = 30. 30 × 7 = 210. 210 - 11 = 199.",
      "20 × 11 = 220. 220 - 15 = 205. 205 - 4 = 201.",
      "25 - 9 = 16. 20 × 16 = 320. 320 + 13 = 333.",
      "10 / 5 = 2. 12 × 2 = 24. 24 × 18 = 432. 432 - 11 = 421."
    ]
  },
  {
    "targets": [55, 175, 225, 355, 495],
    "numbers": [
      [2, 3, 7, 10, 15, 25],
      [3, 4, 5, 11, 20, 25],
      [4, 5, 9, 11, 15, 20],
      [5, 8, 9, 11, 15, 20],
      [5, 6, 10, 11, 18, 12]
    ],
    "solutions": [
      "10 × 7 = 70. 70 - 15 = 55.",
      "4 + 3 = 7. 25 × 7 = 175.",
      "11 + 4 = 15. 15 × 15 = 225.",
      "20 × 15 = 300. 11 × 5 = 55. 300 + 55 = 355.",
      "12 - 10 = 2. 18 / 2 = 9. 11 × 9 = 99.  99 × 5 = 495."
    ]
  },
  {
    "targets": [53, 146, 229, 351, 463],
    "numbers": [
      [1, 3, 4, 5, 10, 25],
      [2, 5, 7, 11, 15, 25],
      [3, 6, 7, 9, 11, 15],
      [4, 6, 7, 8, 11, 20],
      [5, 7, 9, 11, 13, 23]
    ],
    "solutions": [
      "10 × 5 = 50. 50 + 3 = 53.",
      "7 + 2 = 9. 15 × 9 = 135. 135 + 11 = 146.",
      "9 + 7 = 16. 16 × 15 = 240. 240 - 11 = 229.",
      "8 / 4 = 2. 11 + 2 = 13. 20 + 7 = 27. 27 × 13 = 351.",
      "23 + 5 = 28. 28 × 13 = 364. 11 × 9 = 99. 364 + 99 = 463."
    ]
  },
  {
    "targets": [56, 137, 254, 338, 417],
    "numbers": [
      [2, 3, 4, 5, 10, 25],
      [2, 3, 5, 9, 10, 15],
      [3, 8, 11, 15, 20, 25],
      [3, 6, 7, 8, 9, 15],
      [3, 5, 7, 9, 13, 19]
    ],
    "solutions": [
      "5 × 10 = 50. 2 × 3 = 6. 50 + 6 = 56.",
      "15 × 9 = 135. 135 + 2 = 137.",
      "15 - 3 = 12. 20 × 12 = 240. 240 + 25 = 265. 265 - 11 = 254.",
      "15 + 7 = 22. 9 + 6 = 15. 22 × 15 = 330. 330 + 8 = 338.",
      "19 × 3 = 57. 57 × 7 = 399. 399 + 13 = 412. 412 + 5 = 417."
    ]
  },
  {
    "targets": [76, 164, 203, 379, 493],
    "numbers": [
      [1, 2, 3, 5, 10, 25],
      [2, 3, 7, 9, 10, 11],
      [4, 5, 6, 8, 20, 25],
      [3, 6, 8, 9, 15, 20],
      [3, 5, 11, 19, 20, 25]
    ],
    "solutions": [
      "25 × 3 = 75. 75 + 1 = 76.",
      "11 × 7 = 77. 77 × 2 = 154. 154 + 10 = 164.",
      "25 + 8 = 33. 33 × 6 = 198. 20 / 4 = 5. 198 + 5 = 203.",
      "20 × 6 = 120. 120 + 9 = 129. 129 × 3 = 387. 387 - 8 = 379.",
      "25 + 20 = 45. 45 × 11 = 495. 495 - 5 = 490. 490 + 3 = 493."
    ]
  },
  {
    "targets": [85, 105, 276, 321, 428],
    "numbers": [
      [1, 2, 3, 5, 10, 25],
      [2, 3, 7, 9, 10, 11],
      [6, 7, 8, 11, 15, 20],
      [3, 4, 5, 8, 11, 20],
      [3, 5, 11, 13, 19, 20]
    ],
    "solutions": [
      "25 × 3 = 75. 75 + 10 = 85.",
      "11 × 10 = 110. 110 - 3 = 107. 107 - 2 = 105.",
      "20 × 11 = 220. 8 × 7 = 56. 220 + 56 = 276.",
      "5 + 4 = 9. 11 × 9 = 99. 99 + 8 = 107. 107 × 3 = 321.",
      "13 × 3 = 39. 39 × 11 = 429. 429 - 20 = 409. 409 + 19 = 428."
    ]
  },
  {
    "targets": [52, 118, 273, 335, 463],
    "numbers": [
      [1, 2, 3, 4, 5, 25],
      [2, 3, 5, 7, 9, 15],
      [5, 6, 7, 8, 11, 20],
      [4, 7, 8, 9, 11, 20],
      [9, 11, 13, 19, 20, 25]
    ],
    "solutions": [
      "3 × 4 = 12. 25 − 12 = 13. 5 − 1 = 4. 4 × 13 = 52.",
      "15 + 9 = 24. 24 × 5 = 120. 120 - 2 = 118.",
      "8 + 6 = 14. 20 × 14 = 280. 280 - 7 = 273.",
      "8 × 7 = 56. 56 + 11 = 67. 20 / 4 = 5. 67 × 5 = 335.",
      "25 + 20 = 45. 19 - 9 = 10. 45 × 10 = 450. 450 + 13 = 463."
    ]
  },
  {
    "targets": [89, 136, 251, 315, 495],
    "numbers": [
      [1, 3, 4, 5, 10, 25],
      [2, 3, 5, 11, 15, 25],
      [3, 8, 9, 11, 20, 25],
      [3, 5, 6, 7, 9, 11],
      [3, 5, 7, 13, 20, 25]
    ],
    "solutions": [
      "4 + 5 = 9. 9 × 10 = 90. 90 − 1 = 89.",
      "25 × 5 = 125. 125 + 11 = 136.",
      "9 + 3 = 12. 20 × 12 = 240. 240 + 11 = 251.",
      "9 × 5 = 45. 45 × 7 = 315.",
      "25 × 20 = 500. 500 - 5 = 495."
    ]
  },
  {
    "targets": [81, 106, 238, 384, 413],
    "numbers": [
      [1, 2, 3, 4, 10, 25],
      [2, 3, 7, 9, 10, 11],
      [3, 5, 6, 8, 9, 25],
      [4, 5, 6, 8, 9, 15],
      [5, 11, 19, 20, 23, 25]
    ],
    "solutions": [
      "2 × 4 = 8. 8 × 10 = 80. 80 + 1 = 81.",
      "11 × 9 = 99. 99 + 7 = 106.",
      "25 × 9 = 225. 225 + 8 = 233. 233 + 5 = 238.",
      "9 - 8 = 1. 15 + 1 = 16. 6 × 4 = 24. 24 × 16 = 384.",
      "25 - 23 = 2. 20 + 2 = 22. 22 × 19 = 418. 418 - 5 = 413."
    ]
  },
  {
    "targets": [77, 175, 287, 396, 414],
    "numbers": [
      [1, 2, 3, 4, 5, 25],
      [2, 3, 5, 7, 9, 15],
      [5, 6, 7, 11, 20, 25],
      [3, 4, 6, 7, 11, 20],
      [7, 9, 11, 19, 20, 23]
    ],
    "solutions": [
      "5 + 2 = 7. 3 × 4 = 12. 12 − 1 = 11. 7 × 11 = 77.",
      "9 + 3 = 12. 15 × 12 = 180. 180 - 5 = 175.",
      "6 × 5 = 30. 30 + 11 = 41. 41 × 7 = 287.",
      "11 × 4 = 44. 6 + 3 = 9. 44 × 9 = 396.",
      "11 + 7 = 18. 23 × 18 = 414."
    ]
  },
  {
    "targets": [54, 192, 283, 317, 414],
    "numbers": [
      [2, 3, 4, 5, 10, 25],
      [2, 7, 9, 10, 11, 25],
      [3, 5, 6, 8, 9, 11],
      [4, 5, 7, 8, 9, 15],
      [3, 9, 11, 13, 23, 25]
    ],
    "solutions": [
      "5 × 10 = 50. 50 + 4 = 54.",
      "9 + 7 = 16. 10 + 2 = 12. 16 × 12 = 192.",
      "11 + 9 = 20. 8 + 6 = 14. 20 × 14 = 280. 280 + 3 = 283.",
      "9 × 7 = 63. 63 × 5 = 315. 8 / 4 = 2. 315 + 2 = 317.",
      "11 × 3 = 33. 33 + 13 = 46. 46 × 9 = 414."
    ]
  },
  {
    "targets": [64, 112, 207, 319, 494],
    "numbers": [
      [1, 2, 4, 5, 10, 25],
      [2, 3, 5, 7, 10, 25],
      [3, 4, 5, 6, 8, 11],
      [3, 7, 9, 11, 15, 20],
      [9, 11, 13, 19, 23, 25]
    ],
    "solutions": [
      "10 + 4 = 14. 25 × 2 = 50. 50 + 14 = 64.",
      "25 × 5 = 125. 125 - 10 = 115. 115 - 3 = 112.",
      "11 × 6 = 66. 66 + 8 = 74. 74 - 5 = 69. 69 × 3 = 207.",
      "20 + 9 = 29. 29 × 11 = 319.",
      "19 × 13 = 247. 11 - 9 = 2. 247 × 2 = 494."
    ]
  },
  {
    "targets": [64, 124, 296, 351, 477],
    "numbers": [
      [2, 3, 4, 5, 10, 25],
      [2, 3, 5, 10, 15, 25],
      [3, 4, 6, 11, 15, 25],
      [3, 4, 6, 8, 9, 15],
      [3, 5, 9, 13, 19, 25]
    ],
    "solutions": [
      "25 + 10 = 35. 35 - 3 = 32. 32 × 2 = 64.",
      "25 × 5 = 125. 125 - 3 = 122. 122 + 2 = 124.",
      "15 - 3 = 12. 25 × 12 = 300. 300 - 4 = 296.",
      "15 × 6 = 90. 90 × 4 = 360. 360 - 9 = 351.",
      "25 × 19 = 475. 475 + 5 = 480. 480 - 3 = 477."
    ]
  },
  {
    "targets": [61, 106, 229, 356, 435],
    "numbers": [
      [2, 3, 4, 5, 10, 25],
      [2, 5, 7, 10, 11, 25],
      [3, 4, 8, 9, 20, 25],
      [3, 4, 5, 8, 11, 15],
      [3, 5, 7, 13, 20, 25]
    ],
    "solutions": [
      "10 + 2 = 12. 12 × 3 = 36. 36 + 25 = 61.",
      "25 + 11 = 36. 10 × 7 = 70. 70 + 36 = 106.",
      "25 × 9 = 225. 225 + 4 = 229.",
      "15 × 8 = 120. 120 × 3 = 360. 360 - 4 = 356.",
      "25 × 5 = 125. 125 + 20 = 145. 145 × 3 = 435."
    ]
  },
  {
    "targets": [55, 193, 228, 342, 422],
    "numbers": [
      [1, 3, 4, 5, 10, 25],
      [2, 7, 10, 11, 15, 25],
      [4, 7, 11, 15, 20, 25],
      [3, 4, 6, 7, 9, 20],
      [3, 7, 13, 19, 20, 25]
    ],
    "solutions": [
      "1 + 10 = 11. 11 × 5 = 55.",
      "25 × 15 = 375. 375 + 11 = 386. 386 / 2 = 193.",
      "11 × 7 = 77. 77 - 20 = 57. 57 × 4 = 228.",
      "6 × 3 = 18. 20 + 18 = 38. 38 × 9 = 342.",
      "19 × 13 = 247. 25 × 7 = 175. 247 + 175 = 422."
    ]
  },
  {
    "targets": [51, 155, 252, 347, 412],
    "numbers": [
      [1, 2, 3, 4, 5, 10],
      [2, 3, 9, 10, 11, 25],
      [3, 7, 11, 15, 20, 25],
      [3, 4, 6, 7, 9, 20],
      [3, 5, 7, 13, 20, 25]
    ],
    "solutions": [
      "10 × 5 = 50. 50 + 1 = 51. ",
      "10 × 9 = 90. 90 × 2 = 180. 180 - 25 = 155.",
      "25 + 11 = 36. 36 × 7 = 252.",
      "9 × 6 = 54. 54 - 4 = 50. 50 × 7 = 350. 350 - 3 = 347.",
      "20 - 3 = 17. 25 × 17 = 425. 425 - 13 = 412."
    ]
  },
  {
    "targets": [77, 158, 278, 366, 405],
    "numbers": [
      [1, 2, 3, 5, 10, 25],
      [2, 3, 7, 9, 10, 25],
      [3, 5, 9, 11, 15, 25],
      [3, 4, 5, 6, 11, 20],
      [3, 7, 9, 11, 19, 23]
    ],
    "solutions": [
      "2 + 5 = 7. 10 + 1 = 11. 7 × 11 = 77.",
      "25 - 9 = 16. 16 × 10 = 160. 160 - 2 = 158.",
      "25 × 11 = 275. 275 + 3 = 278.",
      "20 × 6 = 120. 120 × 3 = 360. 360 + 11 = 371. 371 - 5 = 366.",
      "23 + 19 = 42. 42 + 3 = 45. 45 × 9 = 405."
    ]
  },
  {
    "targets": [63, 172, 251, 316, 458],
    "numbers": [
      [1, 2, 3, 4, 5, 25],
      [5, 7, 9, 10, 15, 25],
      [4, 5, 7, 9, 11, 25],
      [4, 5, 6, 8, 9, 15],
      [7, 9, 13, 19, 20, 25]
    ],
    "solutions": [
      "3 × 5 = 15. 15 × 4 = 60. 60 + 2 = 62. 62 + 1 = 63.",
      "25 × 7 = 175. 15 / 5 = 3. 175 - 3 = 172.",
      "25 - 7 = 18. 18 + 4 = 22. 22 × 11 = 242. 242 + 9 = 251.",
      "9 × 6 = 54. 54 - 15 = 39. 39 × 8 = 312. 312 + 4 = 316.",
      "25 × 13 = 325. 19 × 7 = 133. 325 + 133 = 458."
    ]
  },
  {
    "targets": [86, 136, 297, 321, 401],
    "numbers": [
      [1, 3, 4, 5, 10, 25],
      [3, 5, 9, 10, 11, 15],
      [3, 4, 5, 7, 9, 15],
      [4, 5, 7, 11, 15, 20],
      [7, 11, 13, 19, 20, 25]
    ],
    "solutions": [
      "25 × 4 = 100. 100 − 10 = 90. 90 − 5 = 85. 85 + 1 = 86.",
      "15 + 10 = 25. 25 × 5 = 125. 125 + 11 = 136.",
      "15 - 4 = 11. 11 × 9 = 99. 99 × 3 = 297.",
      "20 × 11 = 220. 15 × 7 = 105. 220 + 105 = 325. 325 - 4 = 321.",
      "11 - 7 = 4. 19 × 4 = 76. 25 × 13 = 325. 325 + 76 = 401."
    ]
  },
  {
    "targets": [97, 128, 214, 377, 483],
    "numbers": [
      [2, 3, 4, 5, 10, 25],
      [2, 7, 9, 10, 15, 25],
      [3, 6, 8, 11, 15, 25],
      [4, 5, 6, 7, 9, 11],
      [7, 9, 13, 19, 20, 23]
    ],
    "solutions": [
      "25 × 4 = 100. 100 − 3 = 97.",
      "15 × 9 = 135. 135 - 7 = 128.",
      "15 - 6 = 9. 25 × 9 = 225. 225 - 11 = 214.",
      "11 × 4 = 44. 44 + 9 = 53. 53 × 7 = 371. 371 + 6 = 377.",
      "19 + 9 = 28. 28 - 7 = 21. 23 × 21 = 483."
    ]
  },
  {
    "targets": [74, 198, 219, 361, 463],
    "numbers": [
      [1, 2, 3, 4, 5, 25],
      [2, 3, 7, 11, 15, 25],
      [4, 6, 8, 9, 11, 25],
      [3, 4, 5, 8, 9, 15],
      [5, 9, 11, 13, 20, 25]
    ],
    "solutions": [
      "25 × 3 = 75. 75 − 1 = 74.",
      "15 + 3 = 18. 18 × 11 = 198.",
      "25 × 9 = 225. 225 - 6 = 219.",
      "9 × 8 = 72. 72 × 5 = 360. 360 + 4 = 364. 364 - 3 = 361.",
      "25 + 11 = 36. 36 × 13 = 468. 468 - 5 = 463."
    ]
  },
  {
    "targets": [55, 173, 246, 328, 424],
    "numbers": [
      [1, 2, 3, 4, 10, 25],
      [5, 7, 9, 10, 11, 25],
      [3, 4, 5, 6, 20, 25],
      [6, 7, 8, 11, 15, 20],
      [3, 9, 11, 19, 23, 25]
    ],
    "solutions": [
      "10 + 1 = 11. 2 + 3 = 5. 5 × 11 = 55.",
      "25 + 11 = 36. 36 × 5 = 180. 180 - 7 = 173.",
      "25 + 20 = 45. 45 - 4 = 41. 41 × 6 = 246.",
      "20 + 15 = 35. 35 + 6 = 41. 41 × 8 = 328.",
      "25 + 23 = 48. 48 × 9 = 432. 19 - 11 = 8. 432 - 8 = 424."
    ]
  },
  {
    "targets": [62, 141, 241, 317, 422],
    "numbers": [
      [1, 3, 4, 5, 10, 25],
      [2, 3, 5, 7, 10, 15],
      [3, 5, 6, 7, 11, 15],
      [4, 5, 9, 11, 15, 20],
      [7, 9, 11, 13, 20, 25]
    ],
    "solutions": [
      "3 × 4 = 12. 10 × 5 = 50. 50 + 12 = 62.",
      "15 × 10 = 150. 150 - 7 = 143. 143 - 2 = 141",
      "15 + 6 = 21. 21 × 11 = 231. 231 + 7 = 238. 238 + 3 = 241.",
      "15 × 11 = 165. 165 × 9 = 1485. 1485 / 5 = 297. 297 + 20 = 317.",
      "25 + 9 = 34. 34 × 13 = 442. 442 - 20 = 422."
    ]
  },
  {
    "targets": [65, 141, 221, 332, 413],
    "numbers": [
      [1, 2, 3, 4, 5, 25],
      [2, 3, 7, 9, 10, 15],
      [3, 6, 8, 9, 20, 25],
      [4, 5, 8, 11, 15, 20],
      [5, 7, 9, 19, 20, 25]
    ],
    "solutions": [
      "25 × 3 = 75. 5 × 2 = 10. 75 − 10 = 65.",
      "15 × 10 = 150. 150 - 9 = 141.",
      "20 - 8 = 12. 12 / 3 = 4. 25 × 9 = 225. 225 - 4 = 221.",
      "11 × 8 = 88. 88 - 5 = 83. 83 × 4 = 332.",
      "25 - 9 = 16. 20 + 7 = 27. 27 × 16 = 432. 432 - 19 = 413."
    ]
  },
  {
    "targets": [96, 161, 275, 355, 404],
    "numbers": [
      [1, 2, 3, 5, 10, 25],
      [2, 5, 9, 10, 11, 25],
      [3, 5, 8, 15, 20, 25],
      [3, 5, 8, 9, 15, 20],
      [9, 11, 19, 20, 23, 25]
    ],
    "solutions": [
      "3 + 1 = 4. 2 × 5 = 10. 10 × 10 = 100. 100 − 4 = 96.",
      "11 × 10 = 110. 110 - 25 = 85. 85 × 2 = 170. 170 - 9 = 161.",
      "20 × 15 = 300. 300 - 25 = 275",
      "15 + 3 = 18. 20 × 18 = 360. 360 - 5 = 355.",
      "20 + 19 = 39. 39 × 11 = 429. 429 - 25 = 404."
    ]
  },
  {
    "targets": [71, 121, 292, 324, 415],
    "numbers": [
      [1, 2, 3, 4, 5, 10],
      [2, 3, 7, 9, 10, 11],
      [3, 4, 9, 11, 15, 20],
      [3, 5, 8, 9, 11, 20],
      [7, 9, 19, 20, 23, 25]
    ],
    "solutions": [
      "3 + 4 = 7. 7 × 10 = 70. 70 + 1 = 71.",
      "9 + 2 = 11. 11 × 11 = 121.",
      "20 × 15 = 300. 300 - 11 = 289. 289 + 3 = 292",
      "20 + 9 = 29. 29 × 11 = 319. 319 + 5 = 324.",
      "25 - 7 = 18. 23 × 18 = 414. 414 + 20 = 434. 434 - 19 = 415."
    ]
  },
  {
    "targets": [55, 128, 212, 324, 486],
    "numbers": [
      [1, 2, 3, 5, 10, 25],
      [2, 3, 7, 10, 15, 25],
      [3, 4, 7, 11, 15, 25],
      [3, 5, 9, 11, 15, 20],
      [5, 7, 9, 13, 19, 25]
    ],
    "solutions": [
      "10 + 1 = 11. 11 × 5 = 55.",
      "15 - 10 = 5. 25 × 5 = 125. 125 + 3 = 128.",
      "15 + 4 = 19. 19 × 11 = 209. 209 + 3 = 212.",
      "20 + 9 = 29. 29 × 11 = 319. 319 + 5 = 324.",
      "7 × 5 = 35. 35 + 19 = 54. 54 × 9 = 486."
    ]
  },
  {
    "targets": [85, 121, 273, 395, 451],
    "numbers": [
      [2, 3, 4, 5, 10, 25],
      [2, 3, 5, 9, 10, 15],
      [3, 4, 5, 11, 15, 25],
      [3, 5, 7, 8, 15, 20],
      [5, 7, 11, 13, 19, 23]
    ],
    "solutions": [
      "4 + 5 = 9. 9 × 10 = 90. 90 − 3 = 87. 87 − 2 = 85.",
      "15 - 2 = 13. 13 × 10 = 130. 130 - 9 = 121.",
      "25 × 11 = 275. 275 - 5 = 270. 270 + 3 = 273.",
      "8 × 7 = 56. 56 + 20 = 76. 76 × 5 = 380. 380 + 15 = 395.",
      "13 + 11 = 24. 24 × 19 = 456. 456 - 5 = 451."
    ]
  },
  {
    "targets": [77, 123, 214, 393, 455],
    "numbers": [
      [1, 2, 3, 4, 5, 25],
      [3, 5, 7, 9, 10, 25],
      [5, 6, 7, 11, 15, 25],
      [3, 6, 8, 9, 11, 15],
      [3, 5, 9, 13, 19, 25]
    ],
    "solutions": [
      "25 × 3 = 75. 75 + 2 = 77.",
      "25 + 9 = 34. 34 + 7 = 41. 41 × 3 = 123.",
      "15 - 6 = 9. 25 × 9 = 225. 225 - 11 = 214.",
      "15 × 8 = 120. 120 + 11 = 131. 131 × 3 = 393.",
      "25 + 19 = 44. 44 - 9 = 35. 35 × 13 = 455."
    ]
  },
  {
    "targets": [85, 111, 225, 378, 483],
    "numbers": [
      [1, 3, 4, 5, 10, 25],
      [2, 5, 7, 9, 15, 25],
      [4, 6, 8, 9, 11, 20],
      [3, 6, 8, 9, 15, 20],
      [5, 7, 11, 13, 20, 23]
    ],
    "solutions": [
      "5 + 1 = 6. 6 × 10 = 60. 60 + 25 = 85.",
      "9 × 7 = 63. 63 × 2 = 126. 126 - 15 = 111.",
      "20 + 11 = 31. 31 - 6 = 25. 25 × 9 = 225.",
      "8 + 6 = 14. 14 × 9 = 126. 126 × 3 = 378.",
      "23 + 20 = 43. 43 - 5 = 38. 38 × 13 = 494. 494 - 11 = 483."
    ]
  },
  {
    "targets": [52, 156, 259, 383, 474],
    "numbers": [
      [1, 2, 3, 4, 5, 10],
      [2, 5, 7, 10, 11, 25],
      [3, 4, 6, 9, 11, 15],
      [3, 6, 7, 9, 15, 20],
      [5, 9, 11, 13, 23, 25]
    ],
    "solutions": [
      "5 × 10 = 50. 50 + 2 = 52.",
      "7 + 5 = 12. 11 + 2 = 13. 13 × 12 = 156.",
      "15 × 6 = 90. 90 × 3 = 270. 270 - 11 = 259",
      "20 + 6 = 26. 26 × 15 = 390. 390 - 7 = 383.",
      "23 - 5 = 18. 25 × 18 = 450. 450 + 13 = 463. 463 + 11 = 474."
    ]
  },
  {
    "targets": [89, 188, 204, 376, 433],
    "numbers": [
      [1, 3, 4, 5, 10, 25],
      [3, 7, 9, 10, 11, 15],
      [6, 7, 8, 9, 15, 25],
      [3, 6, 8, 9, 11, 20],
      [11, 13, 19, 20, 23, 25]
    ],
    "solutions": [
      "5 + 4 = 9. 9 × 10 = 90. 90 − 1 = 89.",
      "15 + 3 = 18. 18 × 11 = 198. 198 - 10 = 188.",
      "25 + 9 = 34. 34 × 6 = 204.",
      "9 × 3 = 27. 27 + 20 = 47. 47 × 8 = 376.",
      "13 + 11 = 24. 24 × 19 = 456. 456 - 23 = 433."
    ]
  },
  {
    "targets": [56, 176, 277, 355, 443],
    "numbers": [
      [2, 3, 4, 5, 10, 25],
      [3, 5, 7, 9, 11, 15],
      [4, 8, 11, 15, 20, 25],
      [4, 5, 6, 7, 11, 15],
      [5, 9, 11, 13, 20, 23]
    ],
    "solutions": [
      "2 × 3 = 6. 5 × 10 = 50. 50 + 6 = 56.",
      "9 + 7 = 16. 16 × 11 = 176.",
      "25 × 11 = 275. 8 / 4 = 2. 275 + 2 = 277.",
      "15 × 4 = 60. 60 + 11 = 71. 71 × 5 = 355.",
      "23 + 13 = 36. 36 + 11 = 47. 47 × 9 = 423. 423 + 20 = 443."
    ]
  },
  {
    "targets": [74, 193, 216, 336, 499],
    "numbers": [
      [1, 2, 3, 5, 10, 25],
      [5, 7, 10, 11, 15, 25],
      [3, 4, 5, 6, 9, 25],
      [3, 4, 7, 8, 15, 20],
      [3, 7, 13, 20, 23, 25]
    ],
    "solutions": [
      "3 × 25 = 75. 75 − 1 = 74.",
      "25 + 15 = 40. 40 × 5 = 200. 200 - 7 = 193.",
      "9 × 6 = 54. 54 × 4 = 216.",
      "20 + 8 = 28. 15 - 3 = 12. 28 × 12 = 336.",
      "25 - 3 = 22. 23 × 22 = 506. 506 - 7 = 499."
    ]
  },
  {
    "targets": [51, 191, 292, 311, 404],
    "numbers": [
      [1, 2, 3, 5, 10, 25],
      [3, 5, 9, 10, 11, 15],
      [4, 6, 8, 9, 20, 25],
      [3, 5, 6, 7, 9, 15],
      [3, 5, 9, 11, 13, 20]
    ],
    "solutions": [
      "5 × 10 = 50. 50 + 1 = 51.",
      "15 + 5 = 20. 20 × 9 = 180. 180 + 11 = 191.",
      "8 × 6 = 48. 48 + 25 = 73. 73 × 4 = 292.",
      "15 + 7 = 22. 9 + 5 = 14. 22 × 14 = 308. 308 + 3 = 311",
      "13 × 9 = 117. 117 + 11 = 128. 128 × 3 = 384. 384 + 20 = 404."
    ]
  },
  {
    "targets": [77, 108, 259, 304, 448],
    "numbers": [
      [1, 2, 3, 4, 10, 25],
      [2, 3, 5, 9, 10, 11],
      [3, 5, 8, 9, 11, 20],
      [3, 5, 7, 9, 11, 15],
      [3, 9, 11, 13, 23, 25]
    ],
    "solutions": [
      "10 + 1 = 11. 3 + 4 = 7. 7 × 11 = 77.",
      "10 + 2 = 12. 12 × 9 = 108.",
      "11 × 8 = 88. 88 × 3 = 264. 264 - 5 = 259.",
      "15 × 7 = 105. 105 × 3 = 315. 315 - 11 = 304.",
      "25 - 11 = 14. 23 + 9 = 32. 32 × 14 = 448."
    ]
  },
  {
    "targets": [68, 127, 225, 345, 458],
    "numbers": [
      [1, 2, 3, 4, 5, 10],
      [2, 3, 5, 7, 15, 25],
      [5, 6, 9, 11, 15, 20],
      [3, 4, 6, 8, 11, 15],
      [3, 5, 7, 19, 23, 25]
    ],
    "solutions": [
      "10 + 4 = 14. 14 × 5 = 70. 70 - 2 = 68.",
      "25 × 5 = 125. 125 + 2 = 127.",
      "9 + 6 = 15. 15 × 15 = 225.",
      "4 × 3 = 12. 12 + 11 = 23. 23 × 15 = 345.",
      "23 × 19 = 437. 7 × 3 = 21. 437 + 21 = 458."
    ]
  },
  {
    "targets": [87, 196, 226, 384, 432],
    "numbers": [
      [1, 2, 3, 5, 10, 25],
      [3, 5, 7, 9, 11, 15],
      [6, 7, 9, 11, 20, 25],
      [4, 5, 6, 9, 15, 20],
      [5, 7, 9, 11, 13, 23]
    ],
    "solutions": [
      "25 × 3 = 75. 75 + 10 = 85. 85 + 2 = 87.",
      "9 + 5 = 14. 11 + 3 = 14. 14 × 14 = 196.",
      "20 × 11 = 220. 220 + 6 = 226.",
      "20 + 5 = 25. 25 × 15 = 375. 375 + 9 = 384.",
      "23 + 13 = 36. 7 + 5 = 12. 36 × 12 = 432."
    ]
  },
  {
    "targets": [67, 185, 219, 321, 457],
    "numbers": [
      [1, 2, 3, 4, 5, 25],
      [2, 7, 9, 10, 15, 25],
      [3, 4, 6, 9, 11, 20],
      [3, 4, 5, 6, 7, 15],
      [3, 7, 9, 13, 20, 25]
    ],
    "solutions": [
      "25 × 3 = 75. 2 × 4 = 8. 75 − 8 = 67.",
      "25 × 7 = 175. 175 + 10 = 185.",
      "20 × 11 = 220. 220 - 4 = 216. 216 + 3 = 219.",
      "15 × 7 = 105. 105 × 3 = 315. 315 + 6 = 321.",
      "20 + 9 = 29. 13 + 3 = 16. 29 × 16 = 464. 464 - 7 = 457."
    ]
  },
  {
    "targets": [73, 155, 234, 337, 406],
    "numbers": [
      [1, 2, 4, 5, 10, 25],
      [2, 3, 5, 7, 10, 15],
      [4, 5, 6, 8, 9, 25],
      [3, 7, 8, 9, 11, 15],
      [5, 7, 9, 11, 13, 25]
    ],
    "solutions": [
      "2 + 1 = 3. 3 × 25 = 75. 10 ÷ 5 = 2. 75 − 2 = 73.",
      "15 × 10 = 150. 150 + 5 = 155.",
      "25 × 9 = 225. 225 + 5 = 230. 230 + 4 = 234.",
      "11 + 9 = 20. 20 + 3 = 23. 23 × 15 = 345. 345 - 8 = 337.",
      "9 × 5 = 45. 45 + 13 = 58. 58 × 7 = 406."
    ]
  },
  {
    "targets": [66, 162, 224, 341, 445],
    "numbers": [
      [1, 2, 3, 4, 5, 10],
      [2, 3, 5, 9, 11, 25],
      [4, 7, 11, 15, 20, 25],
      [5, 7, 8, 9, 15, 20],
      [3, 9, 13, 19, 20, 23]
    ],
    "solutions": [
      "1 + 10 = 11. 11 × 2 = 22. 22 × 3 = 66.",
      "25 + 11 = 36. 36 / 2 = 18. 18 × 9 = 162.",
      "20 × 11 = 220. 220 + 4 = 224.",
      "15 + 8 = 23. 23 × 7 = 161. 20 × 9 = 180. 180 + 161 = 341.",
      "20 + 19 = 39. 39 - 3 = 36. 36 × 13 = 468. 468 - 23 = 445."
    ]
  },
  {
    "targets": [93, 167, 296, 336, 456],
    "numbers": [
      [1, 2, 3, 4, 10, 25],
      [2, 3, 5, 7, 9, 15],
      [3, 5, 8, 11, 20, 25],
      [4, 7, 8, 9, 11, 15],
      [3, 5, 13, 19, 20, 23]
    ],
    "solutions": [
      "25 × 4 = 100. 10 − 3 = 7. 100 − 7 = 93.",
      "15 + 3 = 18. 18 × 9 = 162. 162 + 5 = 167.",
      "25 + 20 = 45. 45 - 8 = 37. 11 - 3 = 8. 37 × 8 = 296",
      "11 × 9 = 99. 99 - 15 = 84. 84 × 4 = 336.",
      "13 - 5 = 8. 19 × 8 = 152. 152 × 3 = 456."
    ]
  },
  {
    "targets": [72, 113, 212, 317, 428],
    "numbers": [
      [1, 2, 3, 4, 5, 10],
      [2, 3, 5, 10, 11, 25],
      [5, 6, 7, 8, 11, 15],
      [7, 8, 9, 11, 15, 20],
      [3, 7, 11, 13, 19, 20]
    ],
    "solutions": [
      "10 − 2 = 8. 4 + 5 = 9. 9 × 8 = 72.",
      "11 × 10 = 110. 110 + 3 = 113.",
      "15 + 5 = 20. 20 × 11 = 220. 220 - 8 = 212.",
      "20 × 15 = 300. 300 + 9 = 309. 309 + 8 = 317.",
      "19 - 3 = 16. 16 × 13 = 208. 20 × 11 = 220. 220 + 208 = 428."
    ]
  },
  {
    "targets": [65, 159, 294, 357, 456],
    "numbers": [
      [1, 2, 3, 4, 5, 10],
      [2, 3, 9, 10, 15, 25],
      [4, 6, 7, 8, 9, 11],
      [3, 5, 6, 7, 8, 15],
      [5, 7, 9, 13, 19, 20]
    ],
    "solutions": [
      "3 × 2 = 6. 6 × 10 = 60. 60 + 5 = 65.",
      "15 × 10 = 150. 150 + 9 = 159.",
      "9 × 4 = 36. 36 + 6 = 42. 42 × 7 = 294.",
      "8 × 6 = 48. 48 + 3 = 51. 51 × 7 = 357.",
      "20 + 9 = 29. 29 - 5 = 24. 24 × 19 = 456."
    ]
  },
  {
    "targets": [84, 141, 219, 306, 416],
    "numbers": [
      [1, 3, 4, 5, 10, 25],
      [2, 5, 9, 10, 15, 25],
      [4, 7, 9, 11, 15, 20],
      [3, 4, 7, 9, 11, 20],
      [5, 9, 11, 19, 23, 25]
    ],
    "solutions": [
      "5 + 3 = 8. 8 × 10 = 80. 80 + 4 = 84.",
      "15 × 10 = 150. 150 - 9 = 141.",
      "20 + 11 = 31. 31 × 9 = 279. 15 × 4 = 60. 279 - 60 = 219.",
      "20 + 11 = 31. 31 + 3 = 34. 34 × 9 = 306.",
      "19 × 11 = 209. 23 × 9 = 207. 209 + 207 = 416."
    ]
  },
  {
    "targets": [73, 158, 254, 345, 441],
    "numbers": [
      [2, 3, 4, 5, 10, 25],
      [2, 3, 5, 7, 9, 11],
      [4, 7, 8, 9, 11, 25],
      [3, 4, 5, 8, 11, 15],
      [3, 5, 9, 13, 20, 23]
    ],
    "solutions": [
      "25 × 3 = 75. 75 - 2 = 73.",
      "11 × 5 = 55. 55 × 3 = 165. 165 - 7 = 158.",
      "25 + 4 = 29. 29 × 9 = 261. 261 - 7 = 254.",
      "4 × 3 = 12. 12 + 11 = 23. 23 × 15 = 345.",
      "23 × 3 = 69. 69 - 20 = 49. 49 × 9 = 441."
    ]
  },
  {
    "targets": [51, 184, 236, 319, 437],
    "numbers": [
      [1, 2, 3, 4, 10, 25],
      [2, 5, 9, 10, 11, 25],
      [4, 5, 6, 9, 15, 20],
      [3, 4, 6, 7, 9, 15],
      [3, 5, 11, 13, 20, 25]
    ],
    "solutions": [
      "10 + 4 = 14. 14 + 2 = 16. 16 + 1 = 17. 17 × 3 = 51.",
      "25 + 10 = 35. 35 × 5 = 175. 175 + 9 = 184.",
      "9 × 6 = 54. 54 + 5 = 59. 59 × 4 = 236.",
      "15 × 7 = 105. 105 × 3 = 315. 315 + 4 = 319.",
      "20 + 13 = 33. 11 + 3 = 14. 33 × 14 = 462. 462 - 25 = 437."
    ]
  },
  {
    "targets": [95, 144, 228, 318, 431],
    "numbers": [
      [1, 2, 3, 5, 10, 25],
      [2, 7, 9, 10, 11, 25],
      [3, 4, 5, 6, 7, 11],
      [3, 5, 6, 9, 11, 15],
      [5, 11, 13, 19, 23, 25]
    ],
    "solutions": [
      "3 + 1 = 4. 4 × 25 = 100. 100 − 5 = 95.",
      "10 / 2 = 5. 11 + 5 = 16. 16 × 9 = 144.",
      "7 × 5 = 35. 35 + 3 = 38. 38 × 6 = 228.",
      "11 + 9 = 20. 20 × 15 = 300. 6 × 3 = 18. 300 + 18 = 318.",
      "23 - 5 = 18. 25 × 18 = 450. 450 - 19 = 431."
    ]
  },
  {
    "targets": [69, 153, 289, 398, 469],
    "numbers": [
      [1, 3, 4, 5, 10, 25],
      [2, 3, 7, 9, 10, 15],
      [4, 7, 11, 15, 20, 25],
      [3, 5, 7, 9, 11, 20],
      [5, 7, 11, 13, 19, 23]
    ],
    "solutions": [
      "4 + 5 = 9. 25 − 10 = 15. 1 + 3 = 4. 4 × 15 = 60. 60 + 9 = 69.",
      "15 × 10 = 150. 150 + 3 = 153.",
      "20 × 15 = 300. 300 - 11 = 289.",
      "11 + 9 = 20. 20 × 20 = 400. 400 - 7 = 393. 393 + 5 = 398.",
      "23 + 19 = 42. 42 × 11 = 462. 462 + 7 = 469."
    ]
  },
  {
    "targets": [83, 106, 236, 318, 491],
    "numbers": [
      [1, 3, 4, 5, 10, 25],
      [2, 3, 5, 10, 11, 15],
      [4, 5, 6, 7, 8, 20],
      [5, 8, 9, 11, 15, 20],
      [3, 7, 9, 11, 19, 23]
    ],
    "solutions": [
      "25 + 1 = 26. 26 × 3 = 78. 78 + 5 = 83.",
      "10 × 5 = 50. 50 + 3 = 53. 53 × 2 = 106.",
      "7 + 5 = 12. 20 × 12 = 240. 240 - 4 = 236.",
      "20 + 15 = 35. 35 × 9 = 315. 315 + 11 = 326. 326 - 8 = 318",
      "11 × 3 = 33. 33 + 19 = 52. 52 × 9 = 468. 468 + 23 = 491."
    ]
  },
  {
    "targets": [62, 122, 267, 393, 494],
    "numbers": [
      [2, 3, 4, 5, 10, 25],
      [5, 7, 9, 11, 15, 25],
      [5, 7, 8, 11, 15, 25],
      [3, 4, 6, 7, 9, 15],
      [3, 5, 7, 20, 23, 25]
    ],
    "solutions": [
      "3 × 5 = 15. 5 × 4 = 60. 60 + 2 = 62.",
      "11 × 7 = 77. 9 × 5 = 45. 77 + 45 = 122.",
      "25 × 11 = 275. 275 - 8 = 267.",
      "15 × 9 = 135. 135 - 4 = 131. 131 × 3 = 393.",
      "23 + 7 = 30. 30 / 5 = 6. 25 × 20 = 500. 500 - 6 = 494."
    ]
  },
  {
    "targets": [93, 168, 218, 337, 432],
    "numbers": [
      [1, 2, 3, 4, 5, 25],
      [2, 3, 9, 10, 11, 15],
      [6, 8, 9, 15, 20, 25],
      [3, 4, 5, 7, 11, 15],
      [5, 7, 9, 13, 19, 25]
    ],
    "solutions": [
      "25 × 4 = 100. 5 + 2 = 7. 100 − 7 = 93.",
      "15 × 11 = 165. 9 / 3 = 3. 165 + 3 = 168.",
      "25 + 8 = 33. 33 × 6 = 198. 198 + 20 = 218.",
      "15 - 5 = 10. 11 × 10 = 110. 110 × 3 = 330. 330 + 7 = 337.",
      "25 - 7 = 18. 19 + 5 = 24. 24 × 18 = 432."
    ]
  },
  {
    "targets": [76, 131, 271, 312, 493],
    "numbers": [
      [10, 2, 1, 3, 4, 25],
      [9, 7, 25, 2, 11, 3],
      [3, 4, 6, 7, 8, 11],
      [4, 7, 8, 9, 14, 20],
      [9, 11, 14, 21, 23, 25]
    ],
    "solutions": [
      "25 × 3 = 75. 75 + 1 = 76.",
      "11 × 9 = 99. 99 + 25 = 124. 124 + 7 = 131.",
      "11 × 8 = 88. 88 × 3 = 264. 264 + 7 = 271.",
      "20 × 14 = 280. 8 × 4 = 32. 280 + 32 = 312.",
      "25 × 21 = 525. 525 - 23 = 502. 502 - 9 = 493."
    ]
  },
  {
    "targets": [55, 137, 291, 315, 453],
    "numbers": [
      [4, 1, 3, 2, 5, 10],
      [3, 7, 10, 9, 15, 2],
      [3, 7, 8, 11, 15, 25],
      [3, 7, 8, 9, 11, 25],
      [8, 12, 13, 15, 20, 23]
    ],
    "solutions": [
      "10 + 1 = 11. 5 × 11 = 55.",
      "15 × 9 = 135. 135 + 2 = 137.",
      "25 + 15 = 40. 40 × 7 = 280. 280 + 11 = 291.",
      "25 + 3 = 28. 28 × 11 = 308. 308 + 7 = 315.",
      "23 × 20 = 460. 460 - 15 = 445. 445 + 8 = 453."
    ]
  },
  {
    "targets": [84, 134, 243, 319, 414],
    "numbers": [
      [1, 2, 3, 25, 4, 5],
      [25, 11, 5, 9, 2, 7],
      [7, 8, 11, 15, 20, 25],
      [3, 5, 7, 8, 11, 20],
      [3, 4, 11, 17, 21, 24]
    ],
    "solutions": [
      "4 × 3 = 12. 5 + 2 = 7. 12 × 7 = 84.",
      "25 × 5 = 125. 125 + 9 = 134.",
      "20 × 11 = 220. 220 + 15 = 235. 235 + 8 = 243.",
      "7 × 3 = 21. 21 + 8 = 29. 29 × 11 = 319.",
      "21 + 17 = 38. 38 × 11 = 418. 418 - 4 = 414."
    ]
  },
  {
    "targets": [62, 118, 286, 359, 447],
    "numbers": [
      [4, 2, 10, 1, 3, 25],
      [5, 25, 2, 11, 7, 15],
      [3, 4, 9, 11, 15, 25],
      [3, 7, 8, 14, 20, 25],
      [9, 15, 17, 21, 24, 25]
    ],
    "solutions": [
      "25 × 2 = 50. 4 × 3 = 12. 50 + 12 = 62.",
      "25 × 5 = 125. 125 - 7 = 118.",
      "25 × 11 = 275. 275 + 15 = 290. 290 - 4 = 286.",
      "25 × 14 = 350. 350 + 20 = 370. 370 - 8 = 362. 362 - 3 = 359.",
      "25 × 24 = 600. 17 × 9 = 153. 600 - 153 = 447."
    ]
  },
  {
    "targets": [65, 167, 248, 335, 482],
    "numbers": [
      [2, 1, 4, 10, 3, 5],
      [7, 10, 25, 2, 9, 15],
      [3, 4, 5, 9, 11, 20],
      [5, 7, 11, 15, 20, 22],
      [4, 7, 14, 15, 20, 24]
    ],
    "solutions": [
      "10 + 3 = 13. 13 × 5 = 65.",
      "10 - 2 = 8. 25 × 7 = 175. 175 - 8 = 167.",
      "20 + 11 = 31. 5 + 3 = 8. 31 × 8 = 248.",
      "22 × 15 = 330. 330 + 5 = 335.",
      "24 × 20 = 480. 14 / 7 = 2. 480 + 2 = 482."
    ]
  },
  {
    "targets": [52, 139, 224, 375, 415],
    "numbers": [
      [5, 1, 3, 10, 2, 4],
      [11, 10, 5, 3, 9, 2],
      [3, 7, 9, 11, 15, 25],
      [4, 6, 7, 8, 9, 15],
      [11, 13, 14, 18, 19, 21]
    ],
    "solutions": [
      "5 × 10 = 50. 50 + 2 = 52.",
      "11 + 2 = 13. 13 × 10 = 130. 130 + 9 = 139.",
      "15 - 7 = 8. 25 + 3 = 28. 28 × 8 = 224.",
      "8 × 4 = 32. 32 - 7 = 25. 25 × 15 = 375.",
      "21 + 18 = 39. 39 × 11 = 429. 429 - 14 = 415."
    ]
  },
  {
    "targets": [79, 128, 291, 374, 483],
    "numbers": [
      [10, 2, 4, 1, 3, 5],
      [2, 15, 9, 25, 10, 7],
      [5, 6, 7, 9, 20, 25],
      [3, 8, 14, 15, 20, 25],
      [7, 9, 13, 18, 20, 23]
    ],
    "solutions": [
      "5 + 3 = 8. 10 × 8 = 80. 80 - 1 = 79.",
      "15 × 9 = 135. 135 - 7 = 128.",
      "7 + 5 = 12. 25 × 12 = 300. 300 - 9 = 291.",
      "25 + 20 = 45. 45 × 8 = 360. 360 + 14 = 374.",
      "18 - 13 = 5. 9 + 5 = 14. 14 + 7 = 21. 23 × 21 = 483."
    ]
  },
  {
    "targets": [71, 174, 213, 341, 407],
    "numbers": [
      [2, 4, 5, 3, 1, 10],
      [11, 25, 7, 5, 2, 10],
      [3, 4, 6, 9, 11, 15],
      [3, 4, 5, 11, 14, 25],
      [8, 11, 13, 18, 23, 24]
    ],
    "solutions": [
      "10 + 4 = 14. 14 x 5 = 70. 70 + 1 = 71.",
      "11 x 7 = 77. 77 + 10 = 87. 87 x 2 = 174.",
      "15 x 4 = 60. 60 + 11 = 71. 71 x 3 = 213.",
      "25 x 14 = 350. 350 - 5 = 345. 345 - 4 = 341.",
      "24 + 13 = 37. 37 x 11 = 407."
    ]
  },
  {
    "targets": [56, 197, 252, 389, 411],
    "numbers": [
      [2, 1, 3, 5, 10, 4],
      [25, 9, 7, 15, 5, 10],
      [6, 9, 11, 15, 20, 25],
      [3, 5, 6, 15, 20, 22],
      [4, 12, 15, 17, 20, 25]
    ],
    "solutions": [
      "10 + 4 = 14. 3 + 1 = 4. 14 × 4 = 56.",
      "25 + 10 = 35. 35 × 5 = 175. 175 + 15 = 190. 190 + 7 = 197.",
      "25 + 15 = 40. 40 + 11 = 51. 51 - 9 = 42. 42 × 6 = 252.",
      "20 - 3 = 17. 22 × 17 = 374. 374 + 15 = 389.",
      "20 - 17 = 3. 12 × 3 = 36. 25 × 15 = 375. 375 + 36 = 411."
    ]
  },
  {
    "targets": [69, 121, 219, 397, 416],
    "numbers": [
      [1, 10, 3, 4, 2, 5],
      [5, 15, 7, 10, 25, 11],
      [3, 5, 6, 7, 9, 15],
      [3, 7, 8, 15, 20, 22],
      [12, 13, 17, 18, 19, 23]
    ],
    "solutions": [
      "5 + 2 = 7. 10 × 7 = 70. 70 - 1 = 69.",
      "15 - 11 = 4. 25 × 5 = 125. 125 - 4 = 121.",
      "15 × 5 = 75. 75 × 3 = 225. 225 - 6 = 219.",
      "20 + 7 = 27. 27 × 15 = 405. 405 - 8 = 397.",
      "23 × 17 = 391. 391 + 13 = 404. 404 + 12 = 416."
    ]
  },
  {
    "targets": [54, 168, 234, 301, 473],
    "numbers": [
      [1, 4, 2, 10, 5, 3],
      [3, 7, 5, 2, 15, 9],
      [4, 5, 7, 8, 9, 25],
      [6, 7, 8, 14, 20, 25],
      [4, 8, 11, 14, 19, 25]
    ],
    "solutions": [
      "5 × 10 = 50. 50 + 4 = 54.",
      "15 + 9 = 24. 24 × 7 = 168.",
      "25 × 9 = 225. 225 + 5 = 230. 230 + 4 = 234.",
      "25 + 20 = 45. 45 × 7 = 315. 315 - 14 = 301.",
      "25 × 19 = 475. 8 / 4 = 2. 475 - 2 = 473."
    ]
  },
  {
    "targets": [92, 171, 232, 335, 414],
    "numbers": [
      [5, 3, 25, 10, 2, 1],
      [3, 2, 11, 9, 25, 5],
      [5, 7, 9, 11, 20, 25],
      [3, 4, 6, 7, 9, 20],
      [5, 13, 19, 20, 21, 24]
    ],
    "solutions": [
      "25 - 2 = 23. 3 + 1 = 4. 23 × 4 = 92.",
      "11 × 2 = 22. 22 - 3 = 19. 19 × 9 = 171.",
      "25 × 9 = 225. 225 + 7 = 232.",
      "9 × 3 = 27. 27 + 20 = 47. 47 × 7 = 329. 329 + 6 = 335.",
      "21 × 19 = 399. 399 + 20 = 419. 419 - 5 = 414."
    ]
  },
  {
    "targets": [68, 121, 278, 311, 484],
    "numbers": [
      [3, 1, 5, 4, 2, 10],
      [2, 9, 11, 10, 15, 5],
      [4, 5, 7, 8, 9, 15],
      [4, 8, 9, 14, 15, 25],
      [3, 8, 15, 17, 21, 23]
    ],
    "solutions": [
      "10 × 2 = 20. 20 - 3 = 17. 17 × 4 = 68.",
      "9 + 2 = 11. 11 × 11 = 121.",
      "15 + 7 = 22. 9 + 4 = 13. 22 × 13 = 286. 286 - 8 = 278.",
      "25 + 15 = 40. 40 × 8 = 320. 320 - 9 = 311.",
      "23 + 21 = 44. 8 + 3 = 11. 44 × 11 = 484."
    ]
  },
  {
    "targets": [65, 127, 295, 306, 410],
    "numbers": [
      [4, 1, 25, 2, 3, 10],
      [11, 10, 2, 15, 5, 3],
      [5, 6, 8, 9, 15, 25],
      [4, 7, 8, 9, 20, 25],
      [3, 4, 17, 18, 20, 21]
    ],
    "solutions": [
      "25 × 3 = 75. 75 - 10 = 65.",
      "15 - 3 = 12. 12 × 11 = 132. 132 - 5 = 127.",
      "9 × 6 = 54. 54 × 5 = 270. 270 + 25 = 295.",
      "25 + 20 = 45. 45 × 7 = 315. 315 - 9 = 306.",
      "20 + 3 = 23. 23 × 18 = 414. 414 - 4 = 410."
    ]
  },
  {
    "targets": [91, 147, 224, 388, 439],
    "numbers": [
      [4, 3, 2, 5, 1, 25],
      [15, 7, 9, 3, 10, 25],
      [3, 5, 7, 9, 15, 20],
      [6, 7, 9, 11, 20, 22],
      [3, 12, 15, 20, 23, 25]
    ],
    "solutions": [
      "25 + 5 = 30. 30 × 3 = 90. 90 + 1 = 91.",
      "15 × 10 = 150. 150 - 3 = 147.",
      "9 × 3 = 27. 27 + 5 = 32. 32 × 7 = 224.",
      "22 × 20 = 440. 440 + 11 = 451. 9 × 7 = 63. 451 - 63 = 388.",
      "15 + 3 = 18. 23 × 18 = 414. 414 + 25 = 439."
    ]
  },
  {
    "targets": [88, 111, 262, 348, 482],
    "numbers": [
      [25, 2, 3, 1, 10, 4],
      [5, 3, 9, 25, 7, 15],
      [3, 4, 6, 11, 20, 25],
      [4, 11, 14, 15, 20, 25],
      [5, 11, 13, 17, 21, 23]
    ],
    "solutions": [
      "25 - 3 = 22. 22 × 4 = 88.",
      "15 × 7 = 105. 105 + 9 = 114. 114 - 3 = 111.",
      "25 - 3 = 22. 22 × 11 = 242. 242 + 20 = 262.",
      "15 + 11 = 26. 26 × 14 = 364. 364 - 20 = 344. 344 + 4 = 348.",
      "23 × 21 = 483. 483 + 17 = 500. 500 - 13 = 487. 487 - 5 = 482."
    ]
  },
  {
    "targets": [59, 162, 229, 354, 443],
    "numbers": [
      [2, 25, 4, 5, 3, 1],
      [10, 3, 7, 2, 5, 9],
      [3, 5, 6, 11, 20, 25],
      [5, 6, 8, 11, 20, 22],
      [3, 4, 11, 13, 23, 24]
    ],
    "solutions": [
      "25 - 5 = 20. 20 × 3 = 60. 60 - 1 = 59.",
      "5 + 3 = 8. 10 + 8 = 18. 18 × 9 = 162.",
      "20 × 11 = 220. 220 + 6 = 226. 226 + 3 = 229.",
      "11 + 6 = 17. 22 × 17 = 374. 374 - 20 = 354.",
      "23 - 4 = 19. 24 × 19 = 456. 456 - 13 = 443."
    ]
  },
  {
    "targets": [58, 159, 202, 384, 499],
    "numbers": [
      [25, 5, 1, 4, 10, 2],
      [15, 5, 9, 25, 3, 2],
      [3, 4, 6, 7, 8, 15],
      [4, 5, 7, 8, 20, 25],
      [3, 12, 21, 23, 24, 25]
    ],
    "solutions": [
      "25 + 4 = 29. 29 × 2 = 58.",
      "5 × 2 = 10. 15 × 10 = 150. 150 + 9 = 159.",
      "15 + 6 = 21. 7 + 3 = 10. 21 × 10 = 210. 210 - 8 = 202.",
      "7 + 5 = 12. 12 × 8 = 96. 96 × 4 = 384.",
      "25 × 21 = 525. 525 - 23 = 502. 502 - 3 = 499."
    ]
  },
  {
    "targets": [64, 177, 269, 396, 405],
    "numbers": [
      [10, 1, 3, 5, 4, 2],
      [9, 25, 3, 2, 7, 15],
      [3, 6, 7, 9, 15, 20],
      [6, 7, 8, 9, 15, 22],
      [4, 8, 9, 18, 21, 25]
    ],
    "solutions": [
      "10 + 2 = 12. 12 × 5 = 60. 60 + 4 = 64.",
      "25 × 7 = 175. 175 + 2 = 177.",
      "7 + 6 = 13. 20 × 13 = 260. 260 + 9 = 269.",
      "22 + 15 = 37. 37 + 7 = 44. 44 × 9 = 396.",
      "8 / 4 = 2. 21 + 2 = 23. 23 × 18 = 414. 414 - 9 = 405."
    ]
  },
  {
    "targets": [75, 176, 246, 398, 407],
    "numbers": [
      [4, 1, 10, 2, 5, 25],
      [2, 11, 15, 25, 10, 3],
      [3, 6, 7, 8, 9, 15],
      [3, 7, 8, 11, 20, 22],
      [3, 11, 13, 14, 17, 25]
    ],
    "solutions": [
      "5 - 2 = 3. 25 × 3 = 75.",
      "3 × 2 = 6. 10 + 6 = 16. 16 × 11 = 176.",
      "9 + 7 = 16. 16 × 15 = 240. 240 + 6 = 246.",
      "20 × 7 = 140. 140 × 3 = 420. 420 - 22 = 398.",
      "17 × 3 = 51. 51 - 14 = 37. 37 × 11 = 407."
    ]
  },
  {
    "targets": [97, 136, 213, 313, 453],
    "numbers": [
      [25, 4, 5, 1, 10, 2],
      [3, 25, 7, 10, 15, 11],
      [3, 4, 6, 8, 20, 25],
      [3, 7, 9, 15, 20, 25],
      [4, 8, 9, 12, 15, 18]
    ],
    "solutions": [
      "2 + 1 = 3. 25 × 4 = 100. 100 - 3 = 97.",
      "15 / 3 = 5. 25 × 5 = 125. 125 + 11 = 136.",
      "6 + 3 = 9. 25 × 9 = 225. 225 - 20 = 205. 205 + 8 = 213.",
      "25 - 9 = 16. 20 × 16 = 320. 320 - 7 = 313.",
      "18 + 9 = 27. 27 × 15 = 405. 12 × 4 = 48. 405 + 48 = 453."
    ]
  },
  {
    "targets": [61, 162, 232, 314, 466],
    "numbers": [
      [10, 25, 5, 4, 2, 3],
      [9, 11, 3, 2, 15, 7],
      [3, 6, 9, 11, 15, 20],
      [3, 4, 6, 7, 8, 25],
      [3, 11, 12, 18, 24, 25]
    ],
    "solutions": [
      "10 + 2 = 12. 12 × 3 = 36. 36 + 25 = 61.",
      "15 × 11 = 165. 165 - 3 = 162.",
      "20 × 11 = 220. 220 + 15 = 235. 235 - 3 = 232.",
      "7 + 6 = 13. 25 × 13 = 325. 325 - 8 = 317. 317 - 3 = 314.",
      "24 × 18 = 432. 432 + 25 = 457. 457 + 12 = 469. 469 - 3 = 466."
    ]
  },
  {
    "targets": [95, 194, 202, 321, 421],
    "numbers": [
      [10, 1, 3, 2, 4, 25],
      [25, 10, 3, 7, 15, 2],
      [3, 6, 7, 8, 9, 25],
      [3, 9, 11, 20, 22, 25],
      [3, 14, 17, 18, 23, 25]
    ],
    "solutions": [
      "5 × 4 = 100. 10 / 2 = 5. 100 - 5 = 95.",
      "25 + 3 = 28. 28 × 7 = 196. 196 - 2 = 194.",
      "\t25 × 7 = 175. 9 × 3 = 27. 175 + 27 = 202.",
      "25 + 11 = 36. 36 × 9 = 324. 324 - 3 = 321.",
      "25 × 17 = 425. 425 - 18 = 407. 407 + 14 = 421."
    ]
  },
  {
    "targets": [56, 123, 269, 344, 492],
    "numbers": [
      [10, 2, 3, 5, 4, 25],
      [10, 5, 9, 7, 15, 11],
      [4, 7, 8, 11, 20, 25],
      [4, 5, 8, 11, 14, 20],
      [3, 5, 12, 14, 15, 17]
    ],
    "solutions": [
      "25 + 3 = 28. 28 × 2 = 56.",
      "15 + 11 = 26. 26 × 5 = 130. 130 - 7 = 123.",
      "20 + 11 = 31. 31 × 8 = 248. 248 + 25 = 273. 273 - 4 = 269.",
      "20 × 5 = 100. 100 - 14 = 86. 86 × 4 = 344.",
      "17 × 3 = 51. 51 - 15 = 36. 36 × 14 = 504. 504 - 12 = 492."
    ]
  },
  {
    "targets": [54, 158, 214, 337, 456],
    "numbers": [
      [5, 2, 25, 10, 4, 1],
      [9, 25, 7, 10, 5, 3],
      [3, 4, 5, 6, 7, 9],
      [3, 4, 7, 11, 15, 25],
      [3, 13, 14, 15, 19, 23]
    ],
    "solutions": [
      "5 × 10 = 50. 50 + 4 = 54.",
      "10 + 9 = 19. 19 × 7 = 133. 133 + 25 = 158.",
      "7 × 6 = 42. 42 × 5 = 210. 210 + 4 = 214.",
      "25 - 3 = 22. 22 × 15 = 330. 330 + 7 = 337.",
      "23 + 14 = 37. 37 - 13 = 24. 24 × 19 = 456."
    ]
  },
  {
    "targets": [78, 125, 271, 349, 421],
    "numbers": [
      [10, 5, 25, 1, 4, 2],
      [15, 11, 3, 5, 2, 10],
      [4, 5, 11, 15, 20, 25],
      [4, 5, 6, 9, 14, 25],
      [11, 14, 17, 23, 24, 25]
    ],
    "solutions": [
      "25 - 5 = 20. 20 × 4 = 80. 80 - 2 = 78.",
      "15 + 10 = 25. 25 × 5 = 125.",
      "25 × 11 = 275. 275 - 4 = 271.",
      "25 × 14 = 350. 350 - 5 = 345. 345 + 4 = 349.",
      "25 × 23 = 575. 14 × 11 = 154. 575 - 154 = 421."
    ]
  },
  {
    "targets": [57, 142, 203, 326, 404],
    "numbers": [
      [1, 2, 10, 5, 3, 4],
      [5, 25, 3, 10, 9, 2],
      [4, 5, 7, 8, 9, 11],
      [5, 6, 14, 15, 20, 22],
      [8, 11, 14, 17, 19, 20]
    ],
    "solutions": [
      "4 + 2 = 6. 10 × 6 = 60. 60 - 3 = 57.",
      "9 + 5 = 14. 14 × 10 = 140. 140 + 2 = 142.",
      "8 × 5 = 40. 40 - 11 = 29. 29 × 7 = 203.",
      "22 × 15 = 330. 20 / 5 = 4. 330 - 4 = 326.",
      "19 + 17 = 36. 36 × 11 = 396. 396 + 8 = 404."
    ]
  },
  {
    "targets": [67, 111, 291, 317, 483],
    "numbers": [
      [4, 5, 25, 1, 3, 10],
      [15, 3, 9, 7, 2, 10],
      [3, 5, 6, 8, 15, 20],
      [5, 6, 7, 9, 20, 22],
      [4, 7, 8, 12, 13, 15]
    ],
    "solutions": [
      "10 + 4 = 14. 14 × 5 = 70. 70 - 3 = 67.",
      "10 + 2 = 12. 12 × 9 = 108. 108 + 3 = 111.",
      "20 × 15 = 300. 300 - 6 = 294. 294 - 3 = 291.",
      "20 - 6 = 14. 22 × 14 = 308. 308 + 9 = 317.",
      "13 + 12 = 25. 15 + 4 = 19. 25 × 19 = 475. 475 + 8 = 483."
    ]
  },
  {
    "targets": [53, 165, 214, 321, 498],
    "numbers": [
      [4, 5, 2, 25, 1, 3],
      [10, 11, 2, 25, 9, 3],
      [3, 4, 5, 6, 9, 11],
      [3, 4, 11, 15, 20, 22],
      [3, 7, 12, 14, 19, 25]
    ],
    "solutions": [
      "25 × 2 = 50. 50 + 3 = 53.",
      "25 - 10 = 15. 15 × 11 = 165.",
      "11 × 5 = 55. 55 × 4 = 220. 220 - 6 = 214.",
      "22 × 15 = 330. 330 - 20 = 310. 310 + 11 = 321.",
      "25 × 19 = 475. 475 + 14 = 489. 489 + 12 = 501. 501 - 3 = 498."
    ]
  },
  {
    "targets": [64, 174, 286, 322, 413],
    "numbers": [
      [25, 3, 10, 1, 5, 2],
      [3, 15, 5, 11, 2, 7],
      [3, 4, 5, 8, 11, 20],
      [3, 6, 7, 11, 14, 15],
      [3, 7, 8, 14, 15, 17]
    ],
    "solutions": [
      "25 - 2 = 23. 23 × 3 = 69. 69 - 5 = 64.",
      "7 + 2 = 9. 15 × 11 = 165. 165 + 9 = 174",
      "20 + 5 = 25. 25 × 11 = 275. 275 + 8 = 283. 283 + 3 = 286.",
      "15 + 14 = 29. 29 × 11 = 319. 319 + 3 = 322.",
      "14 × 3 = 42. 42 + 17 = 59. 59 × 7 = 413."
    ]
  }
]
