[
  {
    "puzzle": 0,
    "numberFreq": {
      "1": 0.12745098039215685,
      "2": 0.13725490196078433,
      "3": 0.14425770308123248,
      "4": 0.13025210084033614,
      "5": 0.14565826330532214,
      "6": 0,
      "7": 0.014005602240896359,
      "8": 0,
      "9": 0.008403361344537815,
      "10": 0.13865546218487396,
      "11": 0.008403361344537815,
      "12": 0,
      "13": 0,
      "14": 0,
      "15": 0.008403361344537815,
      "16": 0,
      "17": 0,
      "18": 0,
      "19": 0,
      "20": 0,
      "21": 0,
      "22": 0,
      "23": 0,
      "24": 0,
      "25": 0.13725490196078433
    },
    "numberOcc": {
      "1": 91,
      "2": 98,
      "3": 103,
      "4": 93,
      "5": 104,
      "6": 0,
      "7": 10,
      "8": 0,
      "9": 6,
      "10": 99,
      "11": 6,
      "12": 0,
      "13": 0,
      "14": 0,
      "15": 6,
      "16": 0,
      "17": 0,
      "18": 0,
      "19": 0,
      "20": 0,
      "21": 0,
      "22": 0,
      "23": 0,
      "24": 0,
      "25": 98
    },
    "avgSteps": 2.5210084033613445,
    "minSteps": 2,
    "maxSteps": 3,
    "avgTarget": 70.28571428571425,
    "minTarget": 51,
    "maxTarget": 74,
    "minLow": 4,
    "maxLow": 6,
    "avgLow": 5.126050420168066,
    "minHigh": 0,
    "maxHigh": 2,
    "avgHigh": 0.8739495798319326
  },
  {
    "puzzle": 1,
    "numberFreq": {
      "1": 0,
      "2": 0.12044817927170869,
      "3": 0.11484593837535013,
      "4": 0.011204481792717087,
      "5": 0.10084033613445378,
      "6": 0.0028011204481792717,
      "7": 0.1134453781512605,
      "8": 0.011204481792717087,
      "9": 0.10364145658263306,
      "10": 0.10504201680672269,
      "11": 0.09523809523809523,
      "12": 0,
      "13": 0,
      "14": 0,
      "15": 0.10784313725490197,
      "16": 0,
      "17": 0,
      "18": 0,
      "19": 0,
      "20": 0.011204481792717087,
      "21": 0,
      "22": 0,
      "23": 0,
      "24": 0,
      "25": 0.10224089635854341
    },
    "numberOcc": {
      "1": 0,
      "2": 86,
      "3": 82,
      "4": 8,
      "5": 72,
      "6": 2,
      "7": 81,
      "8": 8,
      "9": 74,
      "10": 75,
      "11": 68,
      "12": 0,
      "13": 0,
      "14": 0,
      "15": 77,
      "16": 0,
      "17": 0,
      "18": 0,
      "19": 0,
      "20": 8,
      "21": 0,
      "22": 0,
      "23": 0,
      "24": 0,
      "25": 73
    },
    "avgSteps": 2.689075630252101,
    "minSteps": 2,
    "maxSteps": 4,
    "avgTarget": 149.7058823529413,
    "minTarget": 105,
    "maxTarget": 198,
    "minLow": 4,
    "maxLow": 6,
    "avgLow": 4.6722689075630255,
    "minHigh": 0,
    "maxHigh": 2,
    "avgHigh": 1.3277310924369747
  },
  {
    "puzzle": 2,
    "numberFreq": {
      "1": 0,
      "2": 0,
      "3": 0.09103641456582633,
      "4": 0.08683473389355742,
      "5": 0.08403361344537816,
      "6": 0.09803921568627451,
      "7": 0.08263305322128851,
      "8": 0.07703081232492998,
      "9": 0.10084033613445378,
      "10": 0,
      "11": 0.11764705882352941,
      "12": 0,
      "13": 0,
      "14": 0,
      "15": 0.08543417366946779,
      "16": 0,
      "17": 0,
      "18": 0,
      "19": 0,
      "20": 0.08823529411764706,
      "21": 0,
      "22": 0,
      "23": 0,
      "24": 0,
      "25": 0.08823529411764706
    },
    "numberOcc": {
      "1": 0,
      "2": 0,
      "3": 65,
      "4": 62,
      "5": 60,
      "6": 70,
      "7": 59,
      "8": 55,
      "9": 72,
      "10": 0,
      "11": 84,
      "12": 0,
      "13": 0,
      "14": 0,
      "15": 61,
      "16": 0,
      "17": 0,
      "18": 0,
      "19": 0,
      "20": 63,
      "21": 0,
      "22": 0,
      "23": 0,
      "24": 0,
      "25": 63
    },
    "avgSteps": 3.000000000000001,
    "minSteps": 2,
    "maxSteps": 4,
    "avgTarget": 245.30252100840337,
    "minTarget": 201,
    "maxTarget": 219,
    "minLow": 3,
    "maxLow": 6,
    "avgLow": 4.428571428571427,
    "minHigh": 0,
    "maxHigh": 3,
    "avgHigh": 1.5714285714285714
  },
  {
    "puzzle": 3,
    "numberFreq": {
      "1": 0,
      "2": 0,
      "3": 0.09663865546218488,
      "4": 0.08403361344537816,
      "5": 0.0896358543417367,
      "6": 0.08403361344537816,
      "7": 0.09103641456582633,
      "8": 0.08823529411764706,
      "9": 0.10224089635854341,
      "10": 0,
      "11": 0.09523809523809523,
      "12": 0,
      "13": 0.0028011204481792717,
      "14": 0.015406162464985995,
      "15": 0.09803921568627451,
      "16": 0,
      "17": 0,
      "18": 0,
      "19": 0,
      "20": 0.10364145658263306,
      "21": 0,
      "22": 0.015406162464985995,
      "23": 0.0056022408963585435,
      "24": 0,
      "25": 0.028011204481792718
    },
    "numberOcc": {
      "1": 0,
      "2": 0,
      "3": 69,
      "4": 60,
      "5": 64,
      "6": 60,
      "7": 65,
      "8": 63,
      "9": 73,
      "10": 0,
      "11": 68,
      "12": 0,
      "13": 2,
      "14": 11,
      "15": 70,
      "16": 0,
      "17": 0,
      "18": 0,
      "19": 0,
      "20": 74,
      "21": 0,
      "22": 11,
      "23": 4,
      "24": 0,
      "25": 20
    },
    "avgSteps": 3.361344537815126,
    "minSteps": 2,
    "maxSteps": 4,
    "avgTarget": 346.13445378151255,
    "minTarget": 301,
    "maxTarget": 361,
    "minLow": 2,
    "maxLow": 6,
    "avgLow": 4.386554621848742,
    "minHigh": 0,
    "maxHigh": 4,
    "avgHigh": 1.6134453781512605
  },
  {
    "puzzle": 4,
    "numberFreq": {
      "1": 0,
      "2": 0.0028011204481792717,
      "3": 0.0742296918767507,
      "4": 0.012605042016806723,
      "5": 0.07983193277310924,
      "6": 0.0056022408963585435,
      "7": 0.07282913165266107,
      "8": 0.015406162464985995,
      "9": 0.0742296918767507,
      "10": 0.008403361344537815,
      "11": 0.08543417366946779,
      "12": 0.0196078431372549,
      "13": 0.09243697478991597,
      "14": 0.0196078431372549,
      "15": 0.018207282913165267,
      "16": 0,
      "17": 0.018207282913165267,
      "18": 0.02100840336134454,
      "19": 0.09103641456582633,
      "20": 0.08543417366946779,
      "21": 0.014005602240896359,
      "22": 0,
      "23": 0.07983193277310924,
      "24": 0.015406162464985995,
      "25": 0.0938375350140056
    },
    "numberOcc": {
      "1": 0,
      "2": 2,
      "3": 53,
      "4": 9,
      "5": 57,
      "6": 4,
      "7": 52,
      "8": 11,
      "9": 53,
      "10": 6,
      "11": 61,
      "12": 14,
      "13": 66,
      "14": 14,
      "15": 13,
      "16": 0,
      "17": 13,
      "18": 15,
      "19": 65,
      "20": 61,
      "21": 10,
      "22": 0,
      "23": 57,
      "24": 11,
      "25": 67
    },
    "avgSteps": 3.3529411764705888,
    "minSteps": 2,
    "maxSteps": 4,
    "avgTarget": 448.39495798319325,
    "minTarget": 401,
    "maxTarget": 463,
    "minLow": 0,
    "maxLow": 4,
    "avgLow": 2.588235294117648,
    "minHigh": 2,
    "maxHigh": 6,
    "avgHigh": 3.411764705882353
  }
]